tk_sql_lib/__init__.py
tk_sql_lib/dashboard.py
tk_sql_lib/db.py
tk_sql_lib/logo.png
tk_sql_lib/main.py
tk_sql_lib/test.txt
tk_sql_lib/tz.txt
tk_sql_lib-0.1.dist-info/METADATA
tk_sql_lib-0.1.dist-info/WHEEL
tk_sql_lib-0.1.dist-info/top_level.txt
tk_sql_lib-0.1.dist-info/RECORD
