Metadata-Version: 2.4
Name: tk_sql_lib
Version: 0.1
Summary: A simple exam toolkit for GUI and SQLite3 apps using Tkinter.
Author: susich
Classifier: Programming Language :: Python :: 3
Classifier: License :: OSI Approved :: MIT License
Classifier: Operating System :: OS Independent
Requires-Python: >=3.6
Dynamic: author
Dynamic: classifier
Dynamic: description
Dynamic: description-content-type
Dynamic: requires-python
Dynamic: summary
